gcloud_common_utils/__init__.py
gcloud_common_utils/__version__.py
gcloud_common_utils/blob_helper.py
gcloud_common_utils/blob_helper_local.py
gcloud_common_utils/pubsub_helpers.py
gcloud_common_utils-0.4.1.dist-info/LICENSE
gcloud_common_utils-0.4.1.dist-info/METADATA
gcloud_common_utils-0.4.1.dist-info/WHEEL
gcloud_common_utils-0.4.1.dist-info/top_level.txt
gcloud_common_utils-0.4.1.dist-info/RECORD
